{
  "data": [
    {
      "class_name": "Baby Sensory Play",
      "provider_name": "Little Learners",
      "venue_name": "Toddler Time Center",
      "venue_address": "15 Baby Lane, Anytown, AB1 2CD",
      "usual_day": "Monday",
      "start_time": "10:00",
      "end_time": "11:00",
      "dates_running": ["2025-07-07", "2025-07-14", "2025-07-21", "2025-07-28"],
      "price": 12.00,
      "category": "Sensory & Movement",
      "provider_member": true,
      "bookable": true,
      "class_capacity": 10,
      "spaces_available": 6,
      "min_age": 3,
      "max_age": 12,
      "class_image": "https://www.happity.co.uk/assets/revamp/pictures/categories/Baby_Yoga-a809b6e24ae5b7eaee128ffd749dfb6e10dc87c96981129c0789285f63a4b697.png"
    },
    {
      "class_name": "Toddler Music & Movement",
      "provider_name": "Melody Makers",
      "venue_name": "Playful Sounds Studio",
      "venue_address": "22 Melody Road, Anytown, XY9 8ZW",
      "usual_day": "Tuesday",
      "start_time": "11:00",
      "end_time": "12:00",
      "dates_running": ["2025-07-01", "2025-07-08", "2025-07-15", "2025-07-22"],
      "price": 10.00,
      "category": "Music & Play",
      "provider_member": true,
      "bookable": true,
      "class_capacity": 12,
      "spaces_available": 9,
      "min_age": 12,
      "max_age": 24,
      "class_image": "https://www.happity.co.uk/assets/revamp/pictures/categories/STEM-565f3e1d570cd01be5ae24ccd6f427d186b632274f808834707276a352880557.png"
    },
    {
      "class_name": "Preschool Story & Drama",
      "provider_name": "Story Sprouts",
      "venue_name": "Creative Kids Corner",
      "venue_address": "33 Book Street, Anytown, L10 5GH",
      "usual_day": "Wednesday",
      "start_time": "09:30",
      "end_time": "10:45",
      "dates_running": ["2025-07-02", "2025-07-09", "2025-07-16", "2025-07-23"],
      "price": 15.00,
      "category": "Learning & Creativity",
      "provider_member": true,
      "bookable": true,
      "class_capacity": 15,
      "spaces_available": 11,
      "min_age": 24,
      "max_age": 36,
      "class_image": "https://www.happity.co.uk/assets/revamp/pictures/categories/sensory-a97dfeb2037b18adb0320bd8d9360bc045836ae33f2cd5076742ce59a985fecc.jpg"
    },
    {
      "class_name": "Little Movers & Groovers",
      "provider_name": "Tiny Steps",
      "venue_name": "Dance Discovery Hall",
      "venue_address": "44 Step Lane, Anytown, M23 4JK",
      "usual_day": "Thursday",
      "start_time": "12:30",
      "end_time": "14:30",
      "dates_running": ["2025-07-03", "2025-07-10", "2025-07-17", "2025-07-24"],
      "price": 11.00,
      "category": "Music & Movement",
      "provider_member": true,
      "bookable": true,
      "class_capacity": 10,
      "spaces_available": 8,
      "min_age": 18,
      "max_age": 30,
      "class_image": "https://www.happity.co.uk/assets/revamp/pictures/categories/Swimming_Lessons-1e53b246aeadd8fb27a9fda35ba4bf95002585cc12bc4d6eb1330f2013b4da13.png"
    },
    {
      "class_name": "Preschool Creative Arts",
      "provider_name": "Artful Tots",
      "venue_name": "Rainbow Art Room",
      "venue_address": "55 Paint Road, Anytown, N6 7RS",
      "usual_day": "Friday",
      "start_time": "14:00",
      "end_time": "15:00",
      "dates_running": ["2025-07-04", "2025-07-11", "2025-07-18", "2025-07-25"],
      "price": 14.00,
      "category": "Arts & Crafts",
      "provider_member": true,
      "bookable": false,
      "class_capacity": 12,
      "spaces_available": 7,
      "min_age": 30,
      "max_age": 48,
      "class_image": "https://www.happity.co.uk/assets/revamp/pictures/categories/Dad_Activities-bdc49cdc509e463223f6baac117f29c6dbc816116a7e0b2c10d89f039e32f2f7.png"
    },
    {
      "class_name": "Baby Sign Language",
      "provider_name": "Sign & Say",
      "venue_name": "Quiet Signs Studio",
      "venue_address": "66 Sign Avenue, Anytown, PO1 1AA",
      "usual_day": "Saturday",
      "start_time": "14:15",
      "end_time": "15:30",
      "dates_running": ["2025-07-05", "2025-07-12", "2025-07-19", "2025-07-26"],
      "price": 13.00,
      "category": "Communication & Language",
      "provider_member": true,
      "bookable": true,
      "class_capacity": 8,
      "spaces_available": 5,
      "min_age": 6,
      "max_age": 18,
      "class_image": "https://www.happity.co.uk/assets/revamp/pictures/categories/Breastfeeding-03cacb3bc73f35b246e7fa2535d4284c4a67ee475a87ac567dc69078c57d86a0.png"
    },
    {
      "class_name": "Preschool Science & Discovery",
      "provider_name": "Curious Cubs",
      "venue_name": "Discovery Lab",
      "venue_address": "77 Spark Street, Anytown, S2 9TY",
      "usual_day": "Monday",
      "start_time": "13:00",
      "end_time": "14:30",
      "dates_running": ["2025-07-07", "2025-07-14", "2025-07-21", "2025-07-28"],
      "price": 16.00,
      "category": "Learning & Creativity",
      "provider_member": true,
      "bookable": true,
      "class_capacity": 10,
      "spaces_available": 4,
      "min_age": 36,
      "max_age": 60,
      "class_image": "https://www.happity.co.uk/assets/revamp/pictures/categories/Dance-5593a184ea35dbfd3ec6b5c284cc7796a0be63b4edc70354d2d66482a6f66df0.png"
    },
    {
      "class_name": "Toddler Social Playgroup",
      "provider_name": "Happy Hearts",
      "venue_name": "Friendship Play Center",
      "venue_address": "88 Smile Road, Anytown, W1V 0AA",
      "usual_day": "Tuesday",
      "start_time": "14:30",
      "end_time": "15:50",
      "dates_running": ["2025-07-01", "2025-07-08", "2025-07-15", "2025-07-22"],
      "price": 9.00,
      "category": "Social & Play",
      "provider_member": true,
      "bookable": true,
      "class_capacity": 15,
      "spaces_available": 12,
      "min_age": 20,
      "max_age": 36,
      "class_image": "https://www.happity.co.uk/assets/revamp/pictures/categories/Arts_Crafts-7e9ecde3de661a5a5cd2515964d86dbca12ced1a6f9a81bb7f7a5f180a043f12.png"
    },
    {
      "class_name": "Preschool Rhythmic Play",
      "provider_name": "Rhythmic Roots",
      "venue_name": "Harmony Hall",
      "venue_address": "99 Tune Lane, Anytown, EC4M 6LT",
      "usual_day": "Wednesday",
      "start_time": "11:30",
      "end_time": "13:15",
      "dates_running": ["2025-07-02", "2025-07-09", "2025-07-16", "2025-07-23"],
      "price": 17.00,
      "category": "Music & Movement",
      "provider_member": true,
      "bookable": true,
      "class_capacity": 12,
      "spaces_available": 9,
      "min_age": 28,
      "max_age": 48,
      "class_image": "https://www.happity.co.uk/assets/revamp/pictures/categories/Storytime-2a79551e2005b7dd7da7792aa5e866f656f9d5ac1bffb83dab4cbfca2a35e504.png"
    },
    {
      "class_name": "Baby Massage & Wellbeing",
      "provider_name": "Calm Beginnings",
      "venue_name": "Serenity Space",
      "venue_address": "10 Relax Street, Anytown, SW1A 0AA",
      "usual_day": "Thursday",
      "start_time": "10:00",
      "end_time": "11:20",
      "dates_running": ["2025-07-03", "2025-07-10", "2025-07-17", "2025-07-24"],
      "price": 18.00,
      "category": "Infant Care",
      "provider_member": false,
      "bookable": false,
      "class_capacity": 8,
      "spaces_available": 5,
      "min_age": 2,
      "max_age": 10,
      "class_image": "https://www.happity.co.uk/assets/revamp/pictures/categories/Baby_Massage-0f892fa741bbbe9eb3a9754a41ed3fcadfd35988ce2601f4c09e71ee629541c0.png"
    },
    {
      "class_name": "Preschool Outdoor Exploration",
      "provider_name": "Wild Things",
      "venue_name": "Nature Discovery Park",
      "venue_address": "11 Green Lane, Anytown, NW1 3ER",
      "usual_day": "Friday",
      "start_time": "13:30",
      "end_time": "14:30",
      "dates_running": ["2025-07-04", "2025-07-11", "2025-07-18", "2025-07-25"],
      "price": 15.00,
      "category": "Outdoor Play",
      "provider_member": false,
      "bookable": false,
      "class_capacity": 14,
      "spaces_available": 10,
      "min_age": 32,
      "max_age": 54,
      "class_image": "https://www.happity.co.uk/assets/revamp/pictures/categories/Postnatal_Pilates_Yoga-e015eaa8fd634ff75bdd3342ee2dbf3edb7f8efdfd6cf8dbbd279ab514ecfc9f.png"
    },
    {
      "class_name": "Toddler Storytelling & Rhymes",
      "provider_name": "Rhyme Time",
      "venue_name": "Cozy Corner Library",
      "venue_address": "12 Verse Avenue, Anytown, E14 5LQ",
      "usual_day": "Saturday",
      "start_time": "11:30",
      "end_time": "12:30",
      "dates_running": ["2025-07-05", "2025-07-12", "2025-07-19", "2025-07-26"],
      "price": 11.00,
      "category": "Language & Literacy",
      "provider_member": false,
      "bookable": false,
      "class_capacity": 10,
      "spaces_available": 7,
      "min_age": 15,
      "max_age": 27,
      "class_image": "https://www.happity.co.uk/assets/revamp/pictures/categories/Postnatal_Pilates_Yoga-e015eaa8fd634ff75bdd3342ee2dbf3edb7f8efdfd6cf8dbbd279ab514ecfc9f.png"
    },
    {
      "class_name": "Preschool Construction Play",
      "provider_name": "Build & Learn",
      "venue_name": "Block Zone",
      "venue_address": "13 Brick Street, Anytown, SE1 9GF",
      "usual_day": "Sunday",
      "start_time": "10:00",
      "end_time": "11:20",
      "dates_running": ["2025-02-23", "2025-03-02", "2025-03-09", "2025-03-16"],
      "price": 14.00,
      "category": "Creative Play",
      "provider_member": false,
      "bookable": false,
      "class_capacity": 12,
      "spaces_available": 8,
      "min_age": 26,
      "max_age": 42,
      "class_image": "https://www.happity.co.uk/assets/revamp/pictures/categories/foreign_languages-0c307f81607ba16d34ed111e2b73d2b0e6329280fb485b89ca27eaa07f8b1be6.png"
    },
    {
      "class_name": "Baby Yoga & Relaxation",
      "provider_name": "Little Lotus",
      "venue_name": "Tranquil Tots Studio",
      "venue_address": "14 Calm Place, Anytown, IG1 1AB",
      "usual_day": "Monday",
      "start_time": "11:30",
      "end_time": "13:00",
      "dates_running": ["2025-07-07", "2025-07-14", "2025-07-21", "2025-07-28"],
      "price": 16.00,
      "category": "Infant Care",
      "provider_member": true,
      "bookable": true,
      "class_capacity": 8,
      "spaces_available": 4,
      "min_age": 4,
      "max_age": 16,
      "class_image": "https://www.happity.co.uk/assets/revamp/pictures/categories/Baby_First_Aid-3d5de1253627c1a047ff6915c60ff47f87b5492c0d97a97ec4c5ca2ae8a1f1c2.png"
    },
    {
      "class_name": "Preschool Drama & Imagination",
      "provider_name": "Stage Stars",
      "venue_name": "Imagination Playhouse",
      "venue_address": "15 Act Lane, Anytown, BR1 1GE",
      "usual_day": "Tuesday",
      "start_time": "13:00",
      "end_time": "14:00",
      "dates_running": ["2025-07-01", "2025-07-08", "2025-07-15", "2025-07-22"],
      "price": 17.00,
      "category": "Creative Play",
      "provider_member": true,
      "bookable": true,
      "class_capacity": 10,
      "spaces_available": 6,
      "min_age": 34,
      "max_age": 58,
      "class_image": "https://www.happity.co.uk/assets/revamp/pictures/categories/Drama_Theatre-6adc2d6cdf9a73547df93741196473b0e29dea6008b8722476fa8641284b6a53.png"
    },
    {
      "class_name": "Baby Music & Sensory",
      "provider_name": "Tiny Tunes",
      "venue_name": "Baby Beats Studio",
      "venue_address": "21 Sound Lane, Anytown, SL1 1AA",
      "usual_day": "Wednesday",
      "start_time": "09:00",
      "end_time": "09:45",
      "dates_running": ["2025-02-19", "2025-02-26", "2025-03-05", "2025-03-12"],
      "price": 11.50,
      "category": "Sensory & Movement",
      "provider_member": true,
      "bookable": false,
      "class_capacity": 12,
      "spaces_available": 10,
      "min_age": 6,
      "max_age": 18,
      "class_image": "https://www.happity.co.uk/assets/revamp/pictures/categories/Gym_Gymnastics-73007c3aea32ebbb86cc0b7a81864621e016a090d8887f777e6c8e28d28b9341.png"
    },
    {
      "class_name": "Preschool Creative Writing",
      "provider_name": "Little Authors",
      "venue_name": "Storytime Cottage",
      "venue_address": "22 Pen Street, Anytown, HA9 0AA",
      "usual_day": "Thursday",
      "start_time": "14:30",
      "end_time": "15:30",
      "dates_running": ["2025-07-03", "2025-07-10", "2025-07-17", "2025-07-24"],
      "price": 13.00,
      "category": "Language & Literacy",
      "provider_member": true,
      "bookable": false,
      "class_capacity": 10,
      "spaces_available": 8,
      "min_age": 30,
      "max_age": 54,
      "class_image": "https://www.happity.co.uk/assets/revamp/pictures/categories/Football-fb82cd4a06b0343d1d567e0642d3e14f2346717b5b4775319aacb8b3ca40073e.png"
    },
    {
      "class_name": "Toddler Creative Play",
      "provider_name": "Playful Minds",
      "venue_name": "Imagination Station",
      "venue_address": "23 Toy Road, Anytown, UB8 1AS",
      "usual_day": "Friday",
      "start_time": "16:00",
      "end_time": "17:15",
      "dates_running": ["2025-03-07", "2025-03-14", "2025-03-21", "2025-03-28"],
      "price": 10.50,
      "category": "Creative Play",
      "provider_member": true,
      "bookable": false,
      "class_capacity": 16,
      "spaces_available": 13,
      "min_age": 18,
      "max_age": 30,
      "class_image": "https://www.happity.co.uk/assets/revamp/pictures/categories/Toddler_Group-c5d726f935a1b6919603d921952489379ed53e0312e64525fc882feb694a996f.png"
    },
    {
      "class_name": "Preschool Outdoor Art",
      "provider_name": "Little Picassos",
      "venue_name": "Art in the Park",
      "venue_address": "24 Canvas Lane, Anytown, CM1 1AA",
      "usual_day": "Saturday",
      "start_time": "09:30",
      "end_time": "10:30",
      "dates_running": ["2025-07-05", "2025-07-12", "2025-07-19", "2025-07-26"],
      "price": 15.50,
      "category": "Arts & Crafts",
      "provider_member": false,
      "bookable": false,
      "class_capacity": 12,
      "spaces_available": 9,
      "min_age": 36,
      "max_age": 60,
      "class_image": "https://www.happity.co.uk/assets/revamp/pictures/categories/Forest_School_Outdoor-f505dbef9f3c7445910199869753b5d116ce09402bf6f86b45bd7330f5c45675.png"
    },
    {
      "class_name": "Baby and Toddler Movement",
      "provider_name": "Active Steps",
      "venue_name": "Energy Zone",
      "venue_address": "25 Jump Street, Anytown, CO1 1AB",
      "usual_day": "Sunday",
      "start_time": "12:00",
      "end_time": "14:00",
      "dates_running": ["2025-07-06", "2025-07-13", "2025-07-20", "2025-07-27"],
      "price": 12.00,
      "category": "Music & Play",
      "provider_member": true,
      "bookable": false,
      "class_capacity": 18,
      "spaces_available": 15,
      "min_age": 10,
      "max_age": 24,
      "class_image": "https://www.happity.co.uk/assets/revamp/pictures/categories/Postnatal_Fitness-535a75cf58c2fafbbffabf5d19f8bd9cbe4acb1e3dfab350cbed0ed465723df6.png"
    }
  ]
}
